MANIFEST.in
README.md
setup.py
PyRoget/PyRoget.py
PyRoget/__init__.py
PyRoget.egg-info/PKG-INFO
PyRoget.egg-info/SOURCES.txt
PyRoget.egg-info/dependency_links.txt
PyRoget.egg-info/top_level.txt
PyRoget/roget/add_words.txt
PyRoget/roget/basecat_dict.txt
PyRoget/roget/basecat_parent.txt
PyRoget/roget/cat_num.txt
PyRoget/roget/code_nodes.txt
PyRoget/roget/full_childparent.txt
PyRoget/roget/node_child-parent.txt
PyRoget/roget/node_codes.txt
PyRoget/roget/num_cat.txt
PyRoget/roget/parent_dict.txt
PyRoget/roget/thes_cat.txt
PyRoget/roget/thes_cat_list.txt
PyRoget/roget/thes_dict.txt